{
  "openapi": "3.0.1",
  "info": {
    "title": "Google Sheets API",
    "description": "The Google Sheets API lets you read and modify any aspect of a spreadsheet. Spreadsheets have many settings that let you craft beautiful and functional sheets, so the API has many settings too.With this Google Sheets API block, you can request different endpoints from your Betty Blocks applicationGet a SpreadsheetGet the Values from the SpreadsheetCreate a new Spreadsheet Update ValuesCopy a SpreadsheetAnd many more!",
    "contact": {
      "email": "info@bettyblocks.com"
    },
    "license": {
      "name": "Apache 2.0",
      "url": "http://www.apache.org/licenses/LICENSE-2.0.html"
    },
    "version": "1.0.0"
  },
  "servers": [
    {
      "url": "https://example.betty.app/api/runtime"
    }
  ],
  "tags": [
    {
      "name": "Example",
      "description": "Example"
    }
  ],
  "paths": {
    "/v1/Example": {
      "get": {
        "summary": "Example summary",
        "operationId": "Example",
        "responses": {
          "200": {
            "description": "Valid response",
            "content": {
              "application/json": {
                "schema": {
                  "type": "array",
                  "items": {
                    "$ref": "#/components/schemas/Example"
                  }
                }
              }
            }
          }
        },
        "security": [
          {
            "api_key": ["write:users", "read:users"]
          }
        ]
      }
    }
  },
  "components": {
    "schemas": {
      "Example": {
        "type": "object",
        "properties": {
          "status": {
            "type": "string",
            "enum": ["Online", "Slow", "Offline", "Urgent"]
          },
          "lastOnlineDate": {
            "type": "string",
            "format": "datetime"
          },
          "ExampleNumber": {
            "type": "string"
          },
          "ExampleDescription": {
            "type": "string"
          },
          "ExampleAddress": {
            "type": "string"
          },
          "ExampleCode": {
            "type": "string"
          },
          "Example": {
            "type": "string"
          }
        },
        "xml": {
          "name": "Device"
        }
      }
    },
    "securitySchemes": {
      "api_key": {
        "type": "apiKey",
        "name": "api_key",
        "in": "header"
      }
    }
  }
}
